Metadata-Version: 1.1
Name: sanic-apache-accesslogs
Version: 0.2.1
Summary: Apache Access Logs for Sanic
Home-page: https://github.com/arnulfojr/sanic_apache_accesslogs
Author: Arnulfo Solis
Author-email: arnulfojr94@gmail.com
License: UNKNOWN
Download-URL: https://github.com/arnulfojr/sanic_apache_accesslogs/archive/0.2.1.tar.gz
Keywords: accesslog,access,logs,sanic,plugin
Platform: any
Classifier: Intended Audience :: Developers
Classifier: License :: OSI Approved :: MIT License
Classifier: Operating System :: OS Independent
Classifier: Programming Language :: Python
Classifier: Programming Language :: Python :: 3
Classifier: Programming Language :: Python :: 3.5
Classifier: Programming Language :: Python :: 3.6
Classifier: Programming Language :: Python :: 3.7
Classifier: Programming Language :: Python :: Implementation :: CPython
Classifier: Programming Language :: Python :: Implementation :: PyPy
Classifier: Topic :: Internet :: WWW/HTTP :: Dynamic Content
Classifier: Topic :: Software Development :: Libraries :: Python Modules
